{
  "hash": "c9c26896",
  "configHash": "8928e5aa",
  "lockfileHash": "4b8e34fd",
  "browserHash": "8fe515ab",
  "optimized": {
    "react": {
      "src": "../../node_modules/react/index.js",
      "file": "react.js",
      "fileHash": "8ebf1773",
      "needsInterop": true
    },
    "react-dom/client": {
      "src": "../../node_modules/react-dom/client.js",
      "file": "react-dom_client.js",
      "fileHash": "5b8377cf",
      "needsInterop": true
    }
  },
  "chunks": {
    "chunk-3ARHY7UZ": {
      "file": "chunk-3ARHY7UZ.js"
    }
  }
}